src/__init__.py
ctftestsowwy-7.1.dist-info/METADATA
ctftestsowwy-7.1.dist-info/WHEEL
ctftestsowwy-7.1.dist-info/top_level.txt
ctftestsowwy-7.1.dist-info/RECORD
